moderation_model_mixin/__init__.py
moderation_model_mixin/admin.py
moderation_model_mixin/apps.py
moderation_model_mixin/managers.py
moderation_model_mixin/model_admin_mixins.py
moderation_model_mixin/models.py
moderation_model_mixin/querysets.py
moderation_model_mixin/settings.py
moderation_model_mixin/signals.py
moderation_model_mixin/static/css/moderation_model_mixin.css
moderation_model_mixin/static/js/moderation_model_mixin.js
moderation_model_mixin/templates/admin/moderation/moderation_change_form.html
moderation_model_mixin/templates/admin/moderation/submit_line.html
moderation_model_mixin/templatetags/__init__.py
moderation_model_mixin/templatetags/moderation_admin.py
django_moderation_model_mixin-0.1.1.dist-info/LICENSE.md
django_moderation_model_mixin-0.1.1.dist-info/METADATA
django_moderation_model_mixin-0.1.1.dist-info/WHEEL
django_moderation_model_mixin-0.1.1.dist-info/top_level.txt
django_moderation_model_mixin-0.1.1.dist-info/RECORD
